odoo/addons/shopinvader_product_url/README.rst
odoo/addons/shopinvader_product_url/__init__.py
odoo/addons/shopinvader_product_url/__manifest__.py
odoo/addons/shopinvader_product_url/i18n/shopinvader_product_url.pot
odoo/addons/shopinvader_product_url/models/__init__.py
odoo/addons/shopinvader_product_url/models/product_category.py
odoo/addons/shopinvader_product_url/models/product_template.py
odoo/addons/shopinvader_product_url/readme/CONTRIBUTORS.rst
odoo/addons/shopinvader_product_url/readme/DESCRIPTION.rst
odoo/addons/shopinvader_product_url/schemas/__init__.py
odoo/addons/shopinvader_product_url/schemas/category.py
odoo/addons/shopinvader_product_url/schemas/product.py
odoo/addons/shopinvader_product_url/static/description/index.html
odoo/addons/shopinvader_product_url/tests/__init__.py
odoo/addons/shopinvader_product_url/tests/test_category_url.py
odoo/addons/shopinvader_product_url/tests/test_url_in_schemas.py
odoo_addon_shopinvader_product_url-16.0.1.0.1.dist-info/METADATA
odoo_addon_shopinvader_product_url-16.0.1.0.1.dist-info/WHEEL
odoo_addon_shopinvader_product_url-16.0.1.0.1.dist-info/top_level.txt
odoo_addon_shopinvader_product_url-16.0.1.0.1.dist-info/RECORD
